chemconda/__init__.py
chemconda/cli.py
chemconda/config.py
chemconda/utils.py
chemconda/command/__init__.py
chemconda/command/fetch_conda.py
chemconda/command/import_conda.py
chemconda/command/install_conda.py
chemconda/command/install_packages.py
chemconda/command/new_kernel.py
chemconda/command/publish_conda.py
chemconda/command/rm_kernel.py
chemconda/command/show_info.py
chemconda-0.2.4.dist-info/LICENSE
chemconda-0.2.4.dist-info/METADATA
chemconda-0.2.4.dist-info/WHEEL
chemconda-0.2.4.dist-info/entry_points.txt
chemconda-0.2.4.dist-info/top_level.txt
chemconda-0.2.4.dist-info/RECORD
