Metadata-Version: 2.1
Name: chemconda
Version: 0.2.4
Summary: Install Conda and add ipykernel easily on Jupyter Notebook/Lab.
Home-page: https://github.com/trumanw/chemconda
Author: Truman Wu
Author-email: chunan.woo@gmail.com
License: MIT
Keywords: conda,miniconda,jupyter,ipykernel,AI,chemistry
Platform: UNKNOWN
Classifier: Development Status :: 3 - Alpha
Classifier: Intended Audience :: Developers
Classifier: Topic :: Software Development :: Build Tools
Classifier: License :: OSI Approved :: MIT License
Classifier: Programming Language :: Python :: 3
Classifier: Programming Language :: Python :: 3.4
Classifier: Programming Language :: Python :: 3.5
Classifier: Programming Language :: Python :: 3.6
Classifier: Programming Language :: Python :: 3.7
Classifier: Programming Language :: Python :: 3.8
Classifier: Programming Language :: Python :: 3.9
Requires-Dist: requests
Requires-Dist: Click
Requires-Dist: rich
Requires-Dist: PyYAML
Requires-Dist: boto3
